[
  {
    "shipment": {
      "id": 230,
      "identificationNumber": "322170000230",
      "orders": [
        {
          "loadLevel": "SH",
          "id": 230,
          "orderNumber": "345TY65467",
          "freights": [
            {
              "id": 246,
              "description": "dfgv",
              "unitizedQuantity": {
                "quantity": 4,
                "quantityUom": "CTN"
              },
              "nonUnitizedQuantity": {},
              "weight": {
                "weight": 4,
                "weightUOM": "L",
                "type": "G"
              },
              "dimensions": {
                "dimLength": 4,
                "dimWidth": 4,
                "dimHeight": 4,
                "dimLwhMeasurementUnitTypeId": "N"
              },
              "freightClass": ""
            }
          ]
        }
      ],
      "stops": [
        {
          "id": 460,
          "seqNumber": 2,
          "location": {
            "id": 666,
            "name": "OLD BAYMEADOWS MOVERS INC.",
            "address": {
              "address1": "8230 BAYCENTER RD",
              "address2": "",
              "city": "JACKSONVILLE",
              "state": "FL",
              "postalCode": "32256",
              "country": "USA"
            }
          },
          "apptTypeId": "N",
          "apptSubTypeId": null,
          "schEarliestDateTime": null,
          "schTargetDateTime": null,
          "schLatestDateTime": null,
          "actualArrivedDateTime": null,
          "actualDepartedDateTime": null,
          "contacts": [
            {
              "loadLevel": "SH",
              "id": 1,
              "name": "Robert Kelshall",
              "contactFunctionCodeId": "AJ",
              "contactNumber": {
                "number": "904-329-2423",
                "communicationNumberTypeId": "TE"
              }
            },
            {
              "loadLevel": "SH",
              "id": 2,
              "name": "Robert Kelshall",
              "contactFunctionCodeId": "AJ",
              "contactNumber": {
                "number": "robert@wemovejax.com",
                "communicationNumberTypeId": "EM"
              }
            }
          ],
          "comment": ""
        },
        {
          "id": 459,
          "seqNumber": 1,
          "location": {
            "id": 665,
            "name": "John Lacquey Pinestraw Inc.",
            "locationIdentifier": "LMSSKUSF",
            "address": {
              "address1": "8125 264th St",
              "address2": "",
              "city": "Branford",
              "state": "FL",
              "postalCode": "32008",
              "country": "USA"
            }
          },
          "apptTypeId": "A",
          "apptSubTypeId": null,
          "schEarliestDateTime": null,
          "schTargetDateTime": null,
          "schLatestDateTime": {
            "date": "2017-05-11",
            "time": null
          },
          "actualArrivedDateTime": null,
          "actualDepartedDateTime": null,
          "contacts": [
            {
              "loadLevel": "SR",
              "id": 1110,
              "name": "werfg",
              "contactFunctionCodeId": "AL",
              "contactNumber": {
                "number": "3465765678",
                "communicationNumberTypeId": "WP"
              }
            }
          ],
          "comment": ""
        }
      ],
      "comments": [],
      "references": [
        {
          "loadLevel": "SR",
          "id": 463,
          "loadId": 232,
          "value": "345TY65467",
          "code": "WH",
          "desc": "Master Reference (Link) Number"
        },
        {
          "loadLevel": "SR",
          "id": 464,
          "loadId": 232,
          "value": "234567",
          "code": "$UNKWN",
          "desc": "Unknown (Internal only)"
        }
      ],
      "shipmentStatuses": [],
      "serviceStatuses": [
        {
          "id": 1355,
          "entity": "Shipment",
          "identificationNumber": "322170000230",
          "loadLevelType": "SH",
          "status": "FAILED",
          "description": "UNEXPECTED_EXCEPTION:Unexpected Exception while validating Charges. null",
          "type": "AddCharges",
          "retryCount": 6,
          "responseTimeInMillis": 306,
          "lastCalledDate": "2017-05-26T12:58:11.21"
        },
        {
          "id": 1353,
          "entity": "Shipment",
          "identificationNumber": "322170000230",
          "loadLevelType": "SH",
          "status": "COMPLETED",
          "description": null,
          "type": "Rate",
          "retryCount": 6,
          "responseTimeInMillis": 4402,
          "lastCalledDate": "2017-05-26T12:58:10.768"
        },
        {
          "id": 2803,
          "entity": "Shipment",
          "identificationNumber": "322170000230",
          "loadLevelType": "SH",
          "status": "COMPLETED",
          "description": null,
          "type": "CarrierSelection",
          "retryCount": 1,
          "responseTimeInMillis": 1866,
          "lastCalledDate": "2017-05-26T12:36:03.617"
        },
        {
          "id": 1354,
          "entity": "Shipment",
          "identificationNumber": "322170000230",
          "loadLevelType": "SH",
          "status": "COMPLETED",
          "description": null,
          "type": "Credit",
          "retryCount": 1,
          "responseTimeInMillis": -1,
          "lastCalledDate": "2017-05-11T06:44:56.668"
        },
        {
          "id": 1352,
          "entity": "Shipment",
          "identificationNumber": "322170000230",
          "loadLevelType": "SH",
          "status": "COMPLETED",
          "description": null,
          "type": "Distance",
          "retryCount": 1,
          "responseTimeInMillis": -1,
          "lastCalledDate": "2017-05-11T06:44:54.276"
        }
      ],
      "freightStatus": "PNDG",
      "customer": {
        "name": "FACTORY DIRECT FURNITURE                          ",
        "address": {
          "address1": "301 Broad St                                           ",
          "address2": "                                                       ",
          "address3": "                                                       ",
          "address4": "                                                       ",
          "city": "KINGSPORT                               ",
          "state": "TN ",
          "postalCode": "37660      ",
          "country": "USA"
        },
        "customerContacts": [
          {}
        ],
        "customerProfileIdent": "12011",
        "as400_BillToCode": "FADIFU01"
      },
      "deliveryOption": "WGLV",
      "doNotBill": false,
      "costDivision": "LSFM ",
      "businessUnit": "WERFM",
      "customerServiceContact": {
        "id": 1113,
        "name": "Mike Albright",
        "contactFunctionCodeId": "AJ",
        "contactNumber": {
          "number": "micalbright@werner.com",
          "communicationNumberTypeId": "EA"
        }
      },
      "sourceSystem": "Final Mile",
      "billableDistance": {
        "distance": 94,
        "uom": "Miles",
        "productVersion": "MM19",
        "productName": "Rand McNally"
      },
      "billingStatus": "PNDG"
    },
    "segments": [
      {
        "id": 825,
        "identificationNumber": "323170000825",
        "orders": [
          {
            "loadLevel": "SG",
            "id": 825,
            "orderNumber": "345TY65467",
            "freights": [
              {
                "id": 825,
                "description": "dfgv",
                "unitizedQuantity": {
                  "quantity": 4,
                  "quantityUom": "CTN"
                },
                "nonUnitizedQuantity": {},
                "weight": {
                  "weight": 4,
                  "weightUOM": "L",
                  "type": "G"
                },
                "dimensions": {
                  "dimLength": 4,
                  "dimWidth": 4,
                  "dimHeight": 4,
                  "dimLwhMeasurementUnitTypeId": "N"
                },
                "freightClass": ""
              }
            ]
          }
        ],
        "stops": [
          {
            "id": 1650,
            "seqNumber": 2,
            "location": {
              "id": 666,
              "name": "OLD BAYMEADOWS MOVERS INC.",
              "address": {
                "address1": "8230 BAYCENTER RD",
                "address2": "",
                "city": "JACKSONVILLE",
                "state": "FL",
                "postalCode": "32256",
                "country": "USA"
              }
            },
            "apptTypeId": "N",
            "apptSubTypeId": null,
            "schEarliestDateTime": null,
            "schTargetDateTime": null,
            "schLatestDateTime": null,
            "actualArrivedDateTime": null,
            "actualDepartedDateTime": null,
            "contacts": [
              {
                "loadLevel": "SH",
                "id": 2,
                "name": "Robert Kelshall",
                "contactFunctionCodeId": "AJ",
                "contactNumber": {
                  "number": "robert@wemovejax.com",
                  "communicationNumberTypeId": "EM"
                }
              },
              {
                "loadLevel": "SH",
                "id": 1,
                "name": "Robert Kelshall",
                "contactFunctionCodeId": "AJ",
                "contactNumber": {
                  "number": "904-329-2423",
                  "communicationNumberTypeId": "TE"
                }
              }
            ],
            "comment": ""
          },
          {
            "id": 1649,
            "seqNumber": 1,
            "location": {
              "id": 665,
              "name": "John Lacquey Pinestraw Inc.",
              "locationIdentifier": "LMSSKUSF",
              "address": {
                "address1": "8125 264th St",
                "address2": "",
                "city": "Branford",
                "state": "FL",
                "postalCode": "32008",
                "country": "USA"
              }
            },
            "apptTypeId": "A",
            "apptSubTypeId": null,
            "schEarliestDateTime": null,
            "schTargetDateTime": null,
            "schLatestDateTime": {
              "date": "2017-05-11",
              "time": null
            },
            "actualArrivedDateTime": null,
            "actualDepartedDateTime": null,
            "contacts": [
              {
                "loadLevel": "SR",
                "id": 1110,
                "name": "werfg",
                "contactFunctionCodeId": "AL",
                "contactNumber": {
                  "number": "3465765678",
                  "communicationNumberTypeId": "WP"
                }
              }
            ],
            "comment": ""
          }
        ],
        "comments": [],
        "references": [
          {
            "loadLevel": "SR",
            "id": 463,
            "loadId": 232,
            "value": "345TY65467",
            "code": "WH",
            "desc": "Master Reference (Link) Number"
          },
          {
            "loadLevel": "SR",
            "id": 464,
            "loadId": 232,
            "value": "234567",
            "code": "$UNKWN",
            "desc": "Unknown (Internal only)"
          }
        ],
        "shipmentStatuses": [],
        "serviceStatuses": [
          {
            "id": 3193,
            "entity": "Agent Segment",
            "identificationNumber": "323170000825",
            "loadLevelType": "SG",
            "status": "FAILED",
            "description": "UNEXPECTED_EXCEPTION:Unexpected Exception while validating Charges. null",
            "type": "AddCharges",
            "retryCount": 2,
            "responseTimeInMillis": 456,
            "lastCalledDate": "2017-05-26T12:58:13.787"
          },
          {
            "id": 3192,
            "entity": "Agent Segment",
            "identificationNumber": "323170000825",
            "loadLevelType": "SG",
            "status": "COMPLETED",
            "description": null,
            "type": "Rate",
            "retryCount": 2,
            "responseTimeInMillis": 1014,
            "lastCalledDate": "2017-05-26T12:58:13.161"
          },
          {
            "id": 3194,
            "entity": "Agent Segment",
            "identificationNumber": "323170000825",
            "loadLevelType": "SG",
            "status": "COMPLETED",
            "description": null,
            "type": "OBLT",
            "retryCount": 1,
            "responseTimeInMillis": -1,
            "lastCalledDate": "2017-05-26T12:36:23.025"
          },
          {
            "id": 3191,
            "entity": "Agent Segment",
            "identificationNumber": "323170000825",
            "loadLevelType": "SG",
            "status": "COMPLETED",
            "description": null,
            "type": "Distance",
            "retryCount": 1,
            "responseTimeInMillis": 611,
            "lastCalledDate": "2017-05-26T12:36:12.677"
          }
        ],
        "carrier": {
          "carrierIdent": "100004360",
          "scac": "",
          "name": "OLD BAYMEADOWS MOVERS INC.",
          "email": "jawad@wemovejax.com",
          "contactNumber": "904-731-7223",
          "addressVo": {
            "address1": "8230 BAYCENTER RD",
            "address2": "",
            "city": "JACKSONVILLE",
            "state": "FL",
            "postalCode": "32256",
            "country": "USA"
          }
        },
        "freightStatus": "PNDG",
        "freightExceptions": [],
        "payableDistance": {
          "distance": 94,
          "uom": "Miles",
          "productVersion": "MM19",
          "productName": "Rand McNally"
        },
        "payableStatus": "PNDG"
      }
    ],
    "internetTrackingNumber": "1W322D7AAY02QA6",
    "palletCount": 0
  }
]
